{
  "1":{
    "GeneralForm":"What are the minimum price tickets from to on ?",
    "originalQuery": "?origin=xxx0&destination=xxx1&departure_date=xxx2",
    "replaces":{
      "xxx0":"airport",
      "xxx1":"airport",
      "xxx2":"date"
     },
    "search":"low_fare_search",
    "attributes":{
      "xxx0":"origin",
      "xxx1":"destination",
      "xxx2":"departure_date"
    },
    "properties":{
      "date":"1",
      "airport":"2"
    }
  },
  "2":{
    "GeneralForm":"What will be the price of a ticket from  to  on ?",
    "originalQuery": "?origin=xxx0&destination=xxx1&departure_date=xxx2",
    "replaces":{
    "xxx0":"airport",
      "xxx1":"airport",
      "xxx2":"date"
     },
    "attributes":{
      "origin":"xxx0",
      "destination":"xxx1",
      "departure":"xxx2"
    },
    "properties":{
    "airport":"2",
      "date":"1",
      "price":"0"
    }
  },
  "4":{
    "GeneralForm":"Could you please let me know the available options for a flight to on ",
    "originalQuery": "?origin=WRZ&destination=xxx0&departure_date=xxx1",
    "replaces":{
    "xxx0":"airport",
      "xxx1":"date"

     },
    "properties":{
    "airport":"1",
      "date":"1",
      "price":"0"
    }
  },
  "5":{
    "GeneralForm":"What are the available flights from  to  on ",
    "originalQuery": "?origin=xxx0&destination=xxx1&departure_date=xxx2",
    "replaces":{
    "xxx0":"airport",
      "xxx1":"airport",
      "xxx2":"date"

     },
    "properties":{
    "airport":"2",
      "date":"1",
      "price":"0"
    }
  }
}